biobb_mem/__init__.py
biobb_mem/py.typed
biobb_mem/ambertools/__init__.py
biobb_mem/ambertools/cpptraj_density.py
biobb_mem/fatslim/__init__.py
biobb_mem/fatslim/common.py
biobb_mem/fatslim/fatslim_apl.py
biobb_mem/fatslim/fatslim_membranes.py
biobb_mem/gorder/__init__.py
biobb_mem/gorder/gorder_aa.py
biobb_mem/gorder/gorder_cg.py
biobb_mem/gorder/gorder_ua.py
biobb_mem/lipyphilic_biobb/__init__.py
biobb_mem/lipyphilic_biobb/common.py
biobb_mem/lipyphilic_biobb/lpp_assign_leaflets.py
biobb_mem/lipyphilic_biobb/lpp_flip_flop.py
biobb_mem/lipyphilic_biobb/lpp_zpositions.py
biobb_mem/mdanalysis_biobb/__init__.py
biobb_mem/mdanalysis_biobb/mda_hole.py
biobb_mem/test/__init__.py
biobb_mem-5.2.0.dist-info/licenses/LICENSE
biobb_mem-5.2.0.dist-info/METADATA
biobb_mem-5.2.0.dist-info/WHEEL
biobb_mem-5.2.0.dist-info/entry_points.txt
biobb_mem-5.2.0.dist-info/top_level.txt
biobb_mem-5.2.0.dist-info/RECORD
